kinepy/__init__.py
kinepy/tools.py
kinepy/units.py
kinepy/compilation/__init__.py
kinepy/compilation/graph_operations.py
kinepy/compilation/graphs.py
kinepy/compilation/preparation.py
kinepy/gui/Rect.py
kinepy/gui/__init__.py
kinepy/gui/camera.py
kinepy/gui/drawing_tool.py
kinepy/gui/getters.py
kinepy/gui/grid_manager.py
kinepy/gui/gui_class.py
kinepy/gui/logo.ico
kinepy/gui/system_manager.py
kinepy/interface/__init__.py
kinepy/interface/decorators.py
kinepy/interface/interactions.py
kinepy/interface/joints.py
kinepy/interface/metaclass.py
kinepy/interface/relations.py
kinepy/interface/solid.py
kinepy/interface/system.py
kinepy/math/__init__.py
kinepy/math/calculus.py
kinepy/math/dynamic.py
kinepy/math/geometry.py
kinepy/math/kinematic.py
kinepy/objects/__init__.py
kinepy/objects/interactions.py
kinepy/objects/joints.py
kinepy/objects/relations.py
kinepy/objects/solid.py
kinepy/objects/system.py
kinepy-0.1.7.dist-info/LICENSE
kinepy-0.1.7.dist-info/METADATA
kinepy-0.1.7.dist-info/WHEEL
kinepy-0.1.7.dist-info/top_level.txt
kinepy-0.1.7.dist-info/RECORD
