Metadata-Version: 2.1
Name: kinepy
Version: 0.1.7
Summary: Python library dedicated to plane mechanism simulation
Home-page: https://github.com/valentin-burillier/kinepy
Author: Loïc Chevalier - Valentin Burillier
Keywords: robotics,simulation,dynamics,kinematics,statics,inverse-kinematics,mechanism
Requires: numpy
Requires: matplotlib
Requires: pygame
License-File: LICENSE
Requires-Dist: numpy
Requires-Dist: matplotlib
Requires-Dist: pygame
